PyReconstruct/__init__.py
PyReconstruct/checker.py
PyReconstruct/cli.py
PyReconstruct/run.py
PyReconstruct/traceit.py
PyReconstruct/assets/checker/files/class_series.jser
PyReconstruct/assets/checker/files/shapes1.jser
PyReconstruct/assets/checker/files/shapes2.jser
PyReconstruct/assets/checker/files/shapes_0.tif
PyReconstruct/assets/checker/files/shapes_1.tif
PyReconstruct/assets/checker/files/shapes_2.tif
PyReconstruct/assets/checker/files/shapes_3.tif
PyReconstruct/assets/checker/files/shapes_4.tif
PyReconstruct/assets/checker/files/tforms.txt
PyReconstruct/assets/checker/testing/class_series.jser
PyReconstruct/assets/checker/testing/shapes1.0
PyReconstruct/assets/checker/testing/shapes1.1
PyReconstruct/assets/checker/testing/shapes1.2
PyReconstruct/assets/checker/testing/shapes1.3
PyReconstruct/assets/checker/testing/shapes1.4
PyReconstruct/assets/checker/testing/shapes1.jser
PyReconstruct/assets/checker/testing/shapes1.ser
PyReconstruct/assets/checker/testing/shapes2.jser
PyReconstruct/assets/checker/testing/shapes_0.tif
PyReconstruct/assets/checker/testing/shapes_1.tif
PyReconstruct/assets/checker/testing/shapes_2.tif
PyReconstruct/assets/checker/testing/shapes_3.tif
PyReconstruct/assets/checker/testing/shapes_4.tif
PyReconstruct/assets/checker/testing/tforms.txt
PyReconstruct/assets/img/PyReconstruct.ico
PyReconstruct/assets/img/brightness_down.png
PyReconstruct/assets/img/brightness_up.png
PyReconstruct/assets/img/closedpoly.png
PyReconstruct/assets/img/closedtrace.png
PyReconstruct/assets/img/contrast_down.png
PyReconstruct/assets/img/contrast_up.png
PyReconstruct/assets/img/grid.png
PyReconstruct/assets/img/knife.cur
PyReconstruct/assets/img/knife.png
PyReconstruct/assets/img/logo.png
PyReconstruct/assets/img/main_window.png
PyReconstruct/assets/img/openpoly.png
PyReconstruct/assets/img/opentrace.png
PyReconstruct/assets/img/panzoom.png
PyReconstruct/assets/img/pencil.cur
PyReconstruct/assets/img/pointer.png
PyReconstruct/assets/img/scissors.png
pyreconstruct-1.19.0.dist-info/METADATA
pyreconstruct-1.19.0.dist-info/WHEEL
pyreconstruct-1.19.0.dist-info/entry_points.txt
pyreconstruct-1.19.0.dist-info/top_level.txt
pyreconstruct-1.19.0.dist-info/RECORD
