Metadata-Version: 2.4
Name: pyreconstruct
Version: 1.19.0
Summary: RECONSTRUCT in Python
Home-page: https://github.com/SynapseWeb/PyReconstruct
Author: Julian Falco & Michael Chirillo
Author-email: m.chirillo@utexas.edu
License: GNU GLPv3
Requires-Dist: vtk==9.3.1
Requires-Dist: PySide6==6.5.2
Requires-Dist: opencv-python==4.8.1.78
Requires-Dist: numcodecs==0.15.0
Requires-Dist: numpy==1.24.1
Requires-Dist: scikit-image==0.23.2
Requires-Dist: trimesh==3.18.1
Requires-Dist: vedo==2023.4.7
Requires-Dist: zarr==2.18.2
Requires-Dist: lxml==5.2.2
Requires-Dist: gitpython==3.1.43
Requires-Dist: qdarkstyle==3.2.3
Requires-Dist: cloud-volume==11.0.0
Requires-Dist: tifffile==2024.9.20
Requires-Dist: scipy==1.14.1
Dynamic: author
Dynamic: author-email
Dynamic: description
Dynamic: description-content-type
Dynamic: home-page
Dynamic: license
Dynamic: requires-dist
Dynamic: summary
